{
  "version": "7",
  "dialect": "postgresql",
  "entries": [
    {
      "idx": 0,
      "version": "7",
      "when": 1762866247242,
      "tag": "0000_sticky_marvex",
      "breakpoints": true
    },
    {
      "idx": 1,
      "version": "7",
      "when": 1762866945488,
      "tag": "0001_funny_cardiac",
      "breakpoints": true
    },
    {
      "idx": 2,
      "version": "7",
      "when": 1762958469181,
      "tag": "0002_brief_silver_centurion",
      "breakpoints": true
    },
    {
      "idx": 3,
      "version": "7",
      "when": 1762959041374,
      "tag": "0003_nebulous_sue_storm",
      "breakpoints": true
    },
    {
      "idx": 4,
      "version": "7",
      "when": 1762962794143,
      "tag": "0004_glamorous_rocket_raccoon",
      "breakpoints": true
    },
    {
      "idx": 5,
      "version": "7",
      "when": 1763037210387,
      "tag": "0005_slim_mikhail_rasputin",
      "breakpoints": true
    },
    {
      "idx": 6,
      "version": "7",
      "when": 1763053995311,
      "tag": "0006_worthless_gunslinger",
      "breakpoints": true
    },
    {
      "idx": 7,
      "version": "7",
      "when": 1774726612111,
      "tag": "0007_fresh_randall_flagg",
      "breakpoints": true
    },
    {
      "idx": 8,
      "version": "7",
      "when": 1774798478276,
      "tag": "0008_stale_tony_stark",
      "breakpoints": true
    }
  ]
}